bsf_light/__init__.py
bsf_light/convolutions.py
bsf_light/direct.py
bsf_light/fiber.py
bsf_light/load_save_utils.py
bsf_light/scattered.py
bsf_light/utils.py
bsf_light-1.0.1.dist-info/LICENSE
bsf_light-1.0.1.dist-info/METADATA
bsf_light-1.0.1.dist-info/WHEEL
bsf_light-1.0.1.dist-info/top_level.txt
bsf_light-1.0.1.dist-info/RECORD
