Metadata-Version: 2.1
Name: bsf_light
Version: 1.0.1
Summary: Beams Simple and Fast LIGHT simulation (bsf_light) - Fast light simulation for brain tissue using a beam-spread-function approach
Author: David Berling
Author-email: berling@ksvi.mff.cuni.cz
Requires-Python: >=3.13
License-File: LICENSE
Requires-Dist: numpy >=2.1.3
Requires-Dist: scipy >=1.14.1
Requires-Dist: pyyaml >=6.0.2
Requires-Dist: matplotlib >=3.9.2
